aiocodingame/__init__.py
aiocodingame-1.0.0.dist-info/LICENSE
aiocodingame-1.0.0.dist-info/METADATA
aiocodingame-1.0.0.dist-info/WHEEL
aiocodingame-1.0.0.dist-info/top_level.txt
aiocodingame-1.0.0.dist-info/RECORD
