Metadata-Version: 2.1
Name: aiocodingame
Version: 1.0.0
Summary: ⛔️ DEPRACATED: Asynchronous wrapper for the CodinGame API.
Home-page: https://github.com/takos22/aiocodingame
Author: takos22
Author-email: takos2210@gmail.com
License: MIT
Project-URL: Documentation, https://aiocodingame.readthedocs.io/
Project-URL: Issue tracker, https://github.com/takos22/aiocodingame/issues
Platform: UNKNOWN
Classifier: Programming Language :: Python
Classifier: Programming Language :: Python :: 3
Classifier: Programming Language :: Python :: 3 :: Only
Classifier: Programming Language :: Python :: 3.6
Classifier: Programming Language :: Python :: 3.7
Classifier: Programming Language :: Python :: 3.8
Classifier: Programming Language :: Python :: 3.9
Requires-Python: >=3.6
Requires-Dist: codingame[async]
